drivebuildclient/AIExchangeService.py
drivebuildclient/__init__.py
drivebuildclient/aiExchangeMessages_pb2.py
drivebuildclient/db_handler.py
drivebuildclient/httpUtil.py
drivebuild_client-0.42.dist-info/METADATA
drivebuild_client-0.42.dist-info/WHEEL
drivebuild_client-0.42.dist-info/top_level.txt
drivebuild_client-0.42.dist-info/RECORD
