Metadata-Version: 2.1
Name: drivebuild-client
Version: 0.42
Summary: A client for accessing a DriveBuild MainApp.
Home-page: UNKNOWN
Author: Stefan Huber
Author-email: huberst@fim.uni-passau.de
License: MIT
Project-URL: Source, https://github.com/TrackerSB/DriveBuild
Platform: UNKNOWN
Classifier: Operating System :: OS Independent
Classifier: Programming Language :: Python
Classifier: Programming Language :: Python :: 3
Classifier: Programming Language :: Python :: 3.6
Classifier: Programming Language :: Python :: 3.7
Classifier: Programming Language :: Python :: 3.8
Requires-Python: >=3.6
Requires-Dist: dill
Requires-Dist: flask
Requires-Dist: protobuf
